{"filename":"src/lib/mina_wire_types/mina_base/mina_base_fee_transfer.ml","lines":[{"line":"open Utils","counters":[]},{"line":"","counters":[]},{"line":"module Types = struct","counters":[]},{"line":"  module type S = sig","counters":[]},{"line":"    module Single : sig","counters":[]},{"line":"      module V2 : sig","counters":[]},{"line":"        type t = private","counters":[]},{"line":"          { receiver_pk : Public_key.Compressed.V1.t","counters":[]},{"line":"          ; fee : Currency.Fee.V1.t","counters":[]},{"line":"          ; fee_token : Mina_base_token_id.V2.t","counters":[]},{"line":"          }","counters":[]},{"line":"      end","counters":[]},{"line":"    end","counters":[]},{"line":"","counters":[]},{"line":"    module V2 : sig","counters":[]},{"line":"      type t = private Single.V2.t One_or_two.V1.t","counters":[]},{"line":"    end","counters":[]},{"line":"  end","counters":[]},{"line":"end","counters":[]},{"line":"","counters":[]},{"line":"module M = struct","counters":[]},{"line":"  module Single = struct","counters":[]},{"line":"    module V2 = struct","counters":[]},{"line":"      type t =","counters":[]},{"line":"        { receiver_pk : Public_key.Compressed.V1.t","counters":[]},{"line":"        ; fee : Currency.Fee.V1.t","counters":[]},{"line":"        ; fee_token : Mina_base_token_id.V2.t","counters":[]},{"line":"        }","counters":[]},{"line":"    end","counters":[]},{"line":"  end","counters":[]},{"line":"","counters":[]},{"line":"  module V2 = struct","counters":[]},{"line":"    type t = Single.V2.t One_or_two.V1.t","counters":[]},{"line":"  end","counters":[]},{"line":"end","counters":[]},{"line":"","counters":[]},{"line":"module type Concrete = sig","counters":[]},{"line":"  module Single : sig","counters":[]},{"line":"    module V2 : sig","counters":[]},{"line":"      type t =","counters":[]},{"line":"        { receiver_pk : Public_key.Compressed.V1.t","counters":[]},{"line":"        ; fee : Currency.Fee.V1.t","counters":[]},{"line":"        ; fee_token : Mina_base_token_id.V2.t","counters":[]},{"line":"        }","counters":[]},{"line":"    end","counters":[]},{"line":"  end","counters":[]},{"line":"","counters":[]},{"line":"  module V2 : sig","counters":[]},{"line":"    type t = Single.V2.t One_or_two.V1.t","counters":[]},{"line":"  end","counters":[]},{"line":"end","counters":[]},{"line":"","counters":[]},{"line":"module type Local_sig = Signature(Types).S","counters":[]},{"line":"","counters":[]},{"line":"module Make","counters":[]},{"line":"    (Signature : Local_sig) (F : functor (A : Concrete) -> Signature(A).S) =","counters":[]},{"line":"  F (M)","counters":[]},{"line":"include M","counters":[]}]}